raw_api/__init__.py
django_raw_api-0.4.0.dist-info/LICENSE
django_raw_api-0.4.0.dist-info/METADATA
django_raw_api-0.4.0.dist-info/WHEEL
django_raw_api-0.4.0.dist-info/top_level.txt
django_raw_api-0.4.0.dist-info/RECORD
